protaccel/__init__.py
protaccel/protaccel.py
protaccel-0.301.dist-info/LICENSE
protaccel-0.301.dist-info/METADATA
protaccel-0.301.dist-info/WHEEL
protaccel-0.301.dist-info/top_level.txt
protaccel-0.301.dist-info/RECORD
