Metadata-Version: 2.1
Name: protaccel
Version: 0.301
Summary: Package to infer kinetics from scRNA-seq/feature barcoding data.
Home-page: https://github.com/pachterlab/GSP_2019
Author: Gennady Gorin
Author-email: ggorin@caltech.edu
License: UNKNOWN
Platform: UNKNOWN
Classifier: Programming Language :: Python :: 3
Requires-Python: >=3.6
